README.md
setup.cfg
setup.py
tecli/__init__.py
tecli/__main__.py
tecli/clear.py
tecli/commands.py
tecli/config.py
tecli/create.py
tecli/download.py
tecli/info.py
tecli/login.py
tecli/logs.py
tecli/publish.py
tecli/start.py
tecli/configuration/__init__.py
tecli/configuration/base.py
tecli/run/Dockerfile
tecli/skeleton/requirements.txt
tecli/skeleton/src/__init__.py
tecli/skeleton/src/main.py
trends_earth_cli.egg-info/PKG-INFO
trends_earth_cli.egg-info/SOURCES.txt
trends_earth_cli.egg-info/dependency_links.txt
trends_earth_cli.egg-info/entry_points.txt
trends_earth_cli.egg-info/not-zip-safe
trends_earth_cli.egg-info/requires.txt
trends_earth_cli.egg-info/top_level.txt