Metadata-Version: 1.0
Name: trends-earth-cli
Version: 1.0.3
Summary: Library to interact with trends-earth
Home-page: UNKNOWN
Author: Sergio Gordillo, Raul Requero
Author-email: sergio.gordillo@vizzuality.com,raul.requero@vizzuality.com
License: MIT
Platform: UNKNOWN
